CCU/DPU.v
`include "ALU.v"

module DPU(Abus, Bbus, Rbus, n, cc, Kbus, mData, outEnable);

	//Inputs
	input [3:0] Abus;
	input [3:0] Bbus;
	input [3:0] Rbus;
	input [3:0] n;
	input [7:0] mData;
    input outEnable;
	

	//Outputs
	output [23:0] Kbus;
	output [3:0] cc;
	
	//Memory Block
	reg [7:0] regFile[15:0];
    reg [7:0] accuA;
    reg [7:0] accuB;
	
	//Define I/O
	wire[3:0] Abus;
	wire[3:0] Bbus;
	wire[3:0] Rbus;
	wire[3:0] n;
	wire[3:0] cc;	
	wire[7:0] tr;
	wire[7:0] mData;
    wire outEnable;
    wire writeEnable;

	
	reg[23:0] Kbus;
	//reg[3:0] cc;
	reg [3:0] i;
	
	
	//Fill RegFile with something
	initial begin 
		regFile [12] = 1;
        regFile [13] = 0;
	end
	
	
	//Pass through data to regFile
	always @ (n, Rbus) begin
		if(n == 8) begin
			regFile [Rbus] = mData;
			//$display(" New Data  = %b.  Rbus = %d", regFile [Rbus], Rbus);
			//Kbus = (regFile[9] << 16) + (regFile[10] << 8) + (regFile[11]);
			//$monitor(" Kbus @ new data = %b", Kbus);
		end
        else begin
            accuA = regFile [Abus];
            accuB = regFile [Bbus];
        end
	end
			
		
	
	
	//Run ALU
	ALU U_ALU(
		accuA,
		accuB,
		n,
		cc,
		tr,
        writeEnable
		);
	
	
	//Update the 'Kbus'.  This is causing problems.  THe @ Tr is not ideal and since Rbus might
	// not change... The good data gets lost... added cc??
	always @ (tr, writeEnable) begin
        if (writeEnable == 1) begin 
            //$display("Here: RBus = %d,  tr = %b", Rbus, tr);
            regFile [Rbus] = tr;
            //Kbus = regFile [Rbus];
        end
	end
    
	
	    
    //Print registers
    /*always @ (Rbus) begin
        $display("Printout:");
        for (i=0; i<12; i=i+1) begin
            $display("Bit #%d -> %d", i, regFile[i]);
        end
        $display("\n");
    end*/
    
    
    //Output to Screen (Video)
    always @ (outEnable) begin
        begin
        $display("\nVideo Out:");
        $display("X -> %b", regFile[9]);
        $display("Y -> %b", regFile[10]);
        $display("Colour -> %b", regFile[11]);
        end
    end
            
	
	
	
	//For right now, just fill the regFile with 0 to 13...
	task fill;
	begin
		for (i=0; i<14; i=i+1) begin
			regFile [i] = i;
		end
	end
	endtask
	
	
	
endmodule

CCU/CCU.v
`include "DPU.v"

module CCU(cmd, clk, Kbus);

	//Inputs
	input [7:0] cmd;
	input clk;
	
	//Outputs
	output [23:0] Kbus;
	
	//Wires
	wire cmd;
	wire clk;
	wire [23:0] Kbus;
	wire [3:0] cc;
	
	
	//Registers
	reg [1:0] state;
	reg [3:0] Pstate;
	reg [6:0] Lstate;
	reg[3:0] Abus;
	reg[3:0] Bbus;
	reg[3:0] Rbus;
	reg[3:0] n;
	reg[7:0] mData;
    reg [7:0] tx;
    reg [7:0] txe;
    reg outEnable;
	//reg [24:0] Kbus;
	
	
	initial begin
		state = 0;
		Pstate = 0;
		Lstate = 0;
        outEnable = 0;
	end
	
	//Run at clock
	always @ (posedge clk or negedge clk) begin
    
        //outEnable = 0;
		
		//Idle state
		if(state == 0)
		begin
			case (cmd)
				76:line;
				80:point;
			endcase
            
		end
        else begin
        
            //$monitor("Lstate = %d", Lstate);
            //$display("Lstate = %d", Lstate);
		
		
            //Point state.  Fill X, Y, Color registers.  That's it for now.
            if(state == 1)
            begin
                case (Pstate)
                    1:begin
                        n = 8;
                        Rbus = 9;
                        mData = cmd;
                        Pstate = Pstate + 1;
                        end
                    2:begin
                        n = 8;
                        Rbus = 10;
                        mData = cmd;
                        Pstate = Pstate + 1;
                        end
                    3:begin
                        n = 8;
                        Rbus = 11;
                        mData = cmd;
                        
                        outEnable = ~outEnable;
                        
                        Pstate = 0;
                        state = 0;
                        end
                endcase
            end
            
            
            //Line State.  Run that algorithm
            if(state == 2)
            begin
                //$display("Lstate = %d", Lstate);
                case (Lstate)
                    1:begin //Xs
                        n = 8;
                        Rbus = 5;
                        mData = cmd;
                        tx = cmd;
                        Lstate = Lstate + 1;
                        end
                    2:begin //Ys
                        n = 8;
                        Rbus = 7;
                        mData = cmd;
                        Lstate = Lstate + 1;
                        end
                    3:begin //Xe
                        n = 8;
                        Rbus = 6;
                        mData = cmd;
                        txe = cmd;
                        Lstate = Lstate + 1;
                        end
                    4:begin //Ye
                        n = 8;
                        Rbus = 8;
                        mData = cmd;
                        Lstate = Lstate + 1;
                        end
                    5:begin //Colour
                        n = 8;
                        Rbus = 11;
                        mData = cmd;
                        Lstate = Lstate + 1;
                        end
                    6:begin //Dy
                        n = 1;
                        Rbus = 1;
                        Abus = 8;
                        Bbus = 7;
                        Lstate = Lstate + 1;
                        end
                    7:begin //Dx
                        n = 1;
                        Rbus = 0;
                        Abus = 6;
                        Bbus = 5;
                        Lstate = Lstate + 1;
                        end
                    8:begin //EnoInc
                        n = 2;
                        Rbus = 4;
                        Abus = 1;
                        Lstate = Lstate + 1;
                        end
                    9:begin //Error
                        n = 1;
                        Rbus = 2;
                        Abus = 4;
                        Bbus = 0;
                        Lstate = Lstate + 1;
                        end
                    10:begin //EInc
                        n = 1;
                        Rbus = 3;
                        Abus = 2;
                        Bbus = 0;
                        Lstate = Lstate + 1;
                        end
                    11:begin //X, pass Xs
                        n = 4;
                        Rbus = 9;
                        Abus = 5;
                        Lstate = Lstate + 1;
                        end
                    12:begin //Y, pass Ys
                        n = 5;
                        Rbus = 10;
                        Bbus = 7;
                        Lstate = Lstate + 1;
                        end
                        
                    13: begin //Main loop start.  X = X + 1
                        //$display("State 13");
                        n = 0;
                        Rbus = 9;
                        Abus = 9;
                        Bbus = 12;
                        tx = tx + 1;
                        
                        outEnable = ~outEnable;
                        Lstate = Lstate + 1;
                        end
                    14: begin //Main loop: check error < 0
                        //$display("State 14");
                        n = 6;
                        Rbus = 14;
                        Abus = 2;
                        Bbus = 13;
                        Lstate = 19;
                        end
                    15: begin //Main loop: Set error = error + EnoInc 
                        //$display("State 15");
                        n = 0;
                        Rbus = 2;
                        Abus = 2;
                        Bbus = 4;
                        Lstate = 18;
                        end
                    16: begin //Main loop: Set Y = Y + 1.  P1 of 2.
                        //$display("State 16");
                        n = 0;
                        Rbus = 10;
                        Abus = 10;
                        Bbus = 12;
                        Lstate = Lstate + 1;
                        end
                    17: begin //Set error = error + EInc
                        //$display("State 17");
                        n = 0;
                        Rbus = 2;
                        Abus = 2;
                        Bbus = 3;
                        Lstate = 18;
                        end
                    18: begin //End of loop.  Detrmine if the loop should continue
                        //$display("State 18");
                        if (tx <= txe) begin
                            Lstate = 13;
                        end
                        else begin
                            Lstate = 0;
                            state = 0;
                        end
                        end
                    19: begin
                        //$display("cc [3] = %b", cc[3]);
                        if (cc[3] == 1) begin
                            //Set error = error + EnoInc
                            Lstate = 15;
                            end
                        else begin
                            //Set Y = Y +1   + Set Error = Error + EInc
                            Lstate = 16;
                            end
                        end
                        
                        
                endcase
            end
        end
						
	end
    
    
    //Task: Loop
    /*task loop;
    begin
        while (tx <= txe) begin
        
            //X = X + 1
            n = 0;
            Rbus = 9;
            Abus = 9;
            Bbus = 12;
            tx = tx + 1;
            
            //outEnable = 1;
            
            //Check Error < 0
            n = 6;
            Rbus = 14;
            Abus = 2;
            Bbus = 13;
            if (cc[3] == 1) begin
                //Set error = error + EnoInc
                n = 0;
                Rbus = 2;
                Abus = 2;
                Bbus = 4;
                end
            else begin
                //Set Y = Y +1
                n = 0;
                Rbus = 10;
                Abus = 10;
                Bbus = 12;
                
                //Set Error = Error + EInc
                n = 0;
                Rbus = 2;
                Abus = 2;
                Bbus = 3;
                end
            end
        
        Lstate = 0;
        state = 0;
    end
    endtask*/
        
        
            
                
	
	

	/*//Task: InitError
	task initError;
	begin
		n = 1;
		Abus = 4;
		Bbus = 0;
		Rbus = 2;
	end
	endtask*/
	
	
	//Task: Plot point
	task point;
	begin
		state = 1;
		Pstate = 1;
		$display("Point");
	end
	endtask
	
	
	
	//Task: Plot line
	task line;
	begin
		state = 2;	
		Lstate = 1;
		$display("Line");
	end
	endtask
	
	
	
	DPU U_DPU(Abus, Bbus, Rbus, n, cc, Kbus, mData, outEnable);
	
	
endmodule

CCU/CCU_tb.v
`include "CCU.v"

module CCU_tb();


	reg [7:0] cmd;
	reg clk;
	reg[4:0] i;
	
	wire [23:0] Kbus;
	
	
	initial begin
    
    
        $dumpfile("test3.vcd");
        $dumpvars(2,U_CCU);

		clk = 0;
		i = 0;
        
		
		cmd = 76;
		
		/*for (i=0; i<11; i=i+1) begin
			#5 clk = ~clk;
			//$monitor("K = %b", Kbus);
			
			cmd = cmd - i;
		end*/
        
        #5 clk = ~clk;  //Xs
        cmd = 0;
        
        #5 clk = ~clk; //Ys
        cmd = 0;
        
        #5 clk = ~clk; //Xe
        cmd = 50;
        
        #5 clk = ~clk; //Ye
        cmd = 30;
        
        #5 clk = ~clk; //color
        cmd = 10;
        
        #5 clk = ~clk;
        cmd = 12;
        
        #5 clk = ~clk;
        cmd = 14;
        
        #5 clk = ~clk;
        cmd = 16;
        
        #5 clk = ~clk;
        cmd = 18;
        
        #5 clk = ~clk;
        cmd = 20;
        
        #5 clk = ~clk;
        cmd = 22;
        
        #5 clk = ~clk;
        cmd = 24;
        
        #5 clk = ~clk;
        #5 clk = ~clk;
        #5 clk = ~clk;
        
        
        for (i=0; i<32; i=i+1) begin
			#5 clk = ~clk;
            cmd = 0;
        end


        
	
	end
	
	/*always begin
		#50000000000 clk = ~clk;
		$monitor("K = %b", Kbus);
	end*/
	
	
	CCU U_CCU(cmd, clk, Kbus);
	


	
	
endmodule

CCU/test.vcd
$date
	Mon Apr  2 18:02:53 2012
$end
$version
	Icarus Verilog
$end
$timescale
	1s
$end
$scope module CCU_tb $end
$scope module U_CCU $end
$var wire 24 ! Kbus [23:0] $end
$var wire 4 " cc [3:0] $end
$var wire 1 # clk $end
$var wire 8 $ cmd [7:0] $end
$var reg 4 % Abus [3:0] $end
$var reg 4 & Bbus [3:0] $end
$var reg 7 ' Lstate [6:0] $end
$var reg 4 ( Pstate [3:0] $end
$var reg 4 ) Rbus [3:0] $end
$var reg 8 * mData [7:0] $end
$var reg 4 + n [3:0] $end
$var reg 1 , outEnable $end
$var reg 2 - state [1:0] $end
$var reg 8 . tx [7:0] $end
$var reg 8 / txe [7:0] $end
$upscope $end
$upscope $end
$enddefinitions $end
#0
$dumpvars
bx /
bx .
b10 -
0,
bx +
bx *
bx )
b0 (
b1 '
bx &
bx %
b1001100 $
0#
bx "
bx !
$end
#5
b0 "
b10 '
b0 .
b0 *
b101 )
b1000 +
b0 $
1#
#10
b11 '
b111 )
0#
#15
b100 '
b110010 /
b110010 *
b110 )
b110010 $
1#
#20
b101 '
b11110 *
b1000 )
b11110 $
0#
#25
b110 '
b1010 *
b1011 )
b1010 $
1#
#30
b1 "
b111 '
b111 &
b1000 %
b1 )
b1 +
b1100 $
0#
#35
b1 "
b1000 '
b101 &
b110 %
b0 )
b1110 $
1#
#40
b1 "
b1001 '
b1 %
b100 )
b10 +
b10000 $
0#
#45
b1 "
b1010 '
b0 &
b100 %
b10 )
b1 +
b10010 $
1#
#50
b1 "
b1011 '
b10 %
b11 )
b10100 $
0#
#55
b0 "
b1100 '
b101 %
b1001 )
b100 +
b10110 $
1#
#60
b1101 '
b111 &
b1010 )
b101 +
b11000 $
0#
#65
b1 "
b1110 '
1,
b1 .
b1100 &
b1001 %
b1001 )
b0 +
1#
#70
b100 "
b10011 '
b1101 &
b10 %
b1110 )
b110 +
0#
#75
b10000 '
1#
#80
b1 "
b10001 '
b1100 &
b1010 %
b1010 )
b0 +
b0 $
0#
#85
b1 "
b10010 '
b11 &
b10 %
b10 )
1#
#90
b1101 '
0#
#95
b1 "
b1110 '
0,
b10 .
b1100 &
b1001 %
b1001 )
1#
#100
b1000 "
b10011 '
b1101 &
b10 %
b1110 )
b110 +
0#
#105
b1111 '
1#
#110
b1 "
b10010 '
b100 &
b10 )
b0 +
0#
#115
b1101 '
1#
#120
b1 "
b1110 '
1,
b11 .
b1100 &
b1001 %
b1001 )
0#
#125
b100 "
b10011 '
b1101 &
b10 %
b1110 )
b110 +
1#
#130
b10000 '
0#
#135
b1 "
b10001 '
b1100 &
b1010 %
b1010 )
b0 +
1#
#140
b1 "
b10010 '
b11 &
b10 %
b10 )
0#
#145
b1101 '
1#
#150
b1 "
b1110 '
0,
b100 .
b1100 &
b1001 %
b1001 )
0#
#155
b1000 "
b10011 '
b1101 &
b10 %
b1110 )
b110 +
1#
#160
b1111 '
0#
#165
b1 "
b10010 '
b100 &
b10 )
b0 +
1#
#170
b1101 '
0#
#175
b1 "
b1110 '
1,
b101 .
b1100 &
b1001 %
b1001 )
1#
#180
b100 "
b10011 '
b1101 &
b10 %
b1110 )
b110 +
0#
#185
b10000 '
1#
#190
b1 "
b10001 '
b1100 &
b1010 %
b1010 )
b0 +
0#
#195
b1 "
b10010 '
b11 &
b10 %
b10 )
1#
#200
b1101 '
0#
#205
b1 "
b1110 '
0,
b110 .
b1100 &
b1001 %
b1001 )
1#
#210
b100 "
b10011 '
b1101 &
b10 %
b1110 )
b110 +
0#
#215
b10000 '
1#
#220
b1 "
b10001 '
b1100 &
b1010 %
b1010 )
b0 +
0#
#225
b1 "
b10010 '
b11 &
b10 %
b10 )
1#
#230
b1101 '
0#
#235
b1 "
b1110 '
1,
b111 .
b1100 &
b1001 %
b1001 )
1#
#240
b1000 "
b10011 '
b1101 &
b10 %
b1110 )
b110 +
0#
#245
b1111 '
1#
#250
b1 "
b10010 '
b100 &
b10 )
b0 +
0#
#255
b1101 '
1#
#260
b1 "
b1110 '
0,
b1000 .
b1100 &
b1001 %
b1001 )
0#
#265
b100 "
b10011 '
b1101 &
b10 %
b1110 )
b110 +
1#
#270
b10000 '
0#
#275
b1 "
b10001 '
b1100 &
b1010 %
b1010 )
b0 +
1#
#280
b1 "
b10010 '
b11 &
b10 %
b10 )
0#
#285
b1101 '
1#
#290
b1 "
b1110 '
1,
b1001 .
b1100 &
b1001 %
b1001 )
0#
#295
b1000 "
b10011 '
b1101 &
b10 %
b1110 )
b110 +
1#
#300
b1111 '
0#
#305
b1 "
b10010 '
b100 &
b10 )
b0 +
1#
#310
b1101 '
0#
#315
b1 "
b1110 '
0,
b1010 .
b1100 &
b1001 %
b1001 )
1#
#320
b100 "
b10011 '
b1101 &
b10 %
b1110 )
b110 +
0#
#325
b10000 '
1#
#330
b1 "
b10001 '
b1100 &
b1010 %
b1010 )
b0 +
0#
#335
b1 "
b10010 '
b11 &
b10 %
b10 )
1#
#340
b1101 '
0#
#345
b1 "
b1110 '
1,
b1011 .
b1100 &
b1001 %
b1001 )
1#
#350
b100 "
b10011 '
b1101 &
b10 %
b1110 )
b110 +
0#
#355
b10000 '
1#
#360
b1 "
b10001 '
b1100 &
b1010 %
b1010 )
b0 +
0#
#365
b1 "
b10010 '
b11 &
b10 %
b10 )
1#
#370
b1101 '
0#
#375
b1 "
b1110 '
0,
b1100 .
b1100 &
b1001 %
b1001 )
1#
#380
b1000 "
b10011 '
b1101 &
b10 %
b1110 )
b110 +
0#
#385
b1111 '
1#
#390
b1 "
b10010 '
b100 &
b10 )
b0 +
0#
#395
b1101 '
1#
#400
b1 "
b1110 '
1,
b1101 .
b1100 &
b1001 %
b1001 )
0#
#405
b100 "
b10011 '
b1101 &
b10 %
b1110 )
b110 +
1#
#410
b10000 '
0#
#415
b1 "
b10001 '
b1100 &
b1010 %
b1010 )
b0 +
1#
#420
b1 "
b10010 '
b11 &
b10 %
b10 )
0#
#425
b1101 '
1#
#430
b1 "
b1110 '
0,
b1110 .
b1100 &
b1001 %
b1001 )
0#
#435
b100 "
b10011 '
b1101 &
b10 %
b1110 )
b110 +
1#
#440
b10000 '
0#
#445
b1 "
b10001 '
b1100 &
b1010 %
b1010 )
b0 +
1#
#450
b1 "
b10010 '
b11 &
b10 %
b10 )
0#
#455
b1101 '
1#
#460
b1 "
b1110 '
1,
b1111 .
b1100 &
b1001 %
b1001 )
0#
#465
b1000 "
b10011 '
b1101 &
b10 %
b1110 )
b110 +
1#
#470
b1111 '
0#
#475
b1 "
b10010 '
b100 &
b10 )
b0 +
1#
#480
b1101 '
0#
#485
b1 "
b1110 '
0,
b10000 .
b1100 &
b1001 %
b1001 )
1#
#490
b100 "
b10011 '
b1101 &
b10 %
b1110 )
b110 +
0#
#495
b10000 '
1#
#500
b1 "
b10001 '
b1100 &
b1010 %
b1010 )
b0 +
0#
#505
b1 "
b10010 '
b11 &
b10 %
b10 )
1#
#510
b1101 '
0#
#515
b1 "
b1110 '
1,
b10001 .
b1100 &
b1001 %
b1001 )
1#
#520
b1000 "
b10011 '
b1101 &
b10 %
b1110 )
b110 +
0#
#525
b1111 '
1#
#530
b1 "
b10010 '
b100 &
b10 )
b0 +
0#
#535
b1101 '
1#
#540
b1 "
b1110 '
0,
b10010 .
b1100 &
b1001 %
b1001 )
0#
#545
b100 "
b10011 '
b1101 &
b10 %
b1110 )
b110 +
1#
#550
b10000 '
0#
#555
b1 "
b10001 '
b1100 &
b1010 %
b1010 )
b0 +
1#
#560
b1 "
b10010 '
b11 &
b10 %
b10 )
0#
#565
b1101 '
1#
#570
b1 "
b1110 '
1,
b10011 .
b1100 &
b1001 %
b1001 )
0#
#575
b100 "
b10011 '
b1101 &
b10 %
b1110 )
b110 +
1#
#580
b10000 '
0#
#585
b1 "
b10001 '
b1100 &
b1010 %
b1010 )
b0 +
1#
#590
b1 "
b10010 '
b11 &
b10 %
b10 )
0#
#595
b1101 '
1#
#600
b1 "
b1110 '
0,
b10100 .
b1100 &
b1001 %
b1001 )
0#
#605
b1000 "
b10011 '
b1101 &
b10 %
b1110 )
b110 +
1#
#610
b1111 '
0#
#615
b1 "
b10010 '
b100 &
b10 )
b0 +
1#
#620
b1101 '
0#
#625
b1 "
b1110 '
1,
b10101 .
b1100 &
b1001 %
b1001 )
1#
#630
b100 "
b10011 '
b1101 &
b10 %
b1110 )
b110 +
0#
#635
b10000 '
1#
#640
b1 "
b10001 '
b1100 &
b1010 %
b1010 )
b0 +
0#
#645
b1 "
b10010 '
b11 &
b10 %
b10 )
1#
#650
b1101 '
0#
#655
b1 "
b1110 '
0,
b10110 .
b1100 &
b1001 %
b1001 )
1#
#660
b1000 "
b10011 '
b1101 &
b10 %
b1110 )
b110 +
0#
#665
b1111 '
1#
#670
b1 "
b10010 '
b100 &
b10 )
b0 +
0#
#675
b1101 '
1#
#680
b1 "
b1110 '
1,
b10111 .
b1100 &
b1001 %
b1001 )
0#
#685
b100 "
b10011 '
b1101 &
b10 %
b1110 )
b110 +
1#
#690
b10000 '
0#
#695
b1 "
b10001 '
b1100 &
b1010 %
b1010 )
b0 +
1#
#700
b1 "
b10010 '
b11 &
b10 %
b10 )
0#
#705
b1101 '
1#
#710
b1 "
b1110 '
0,
b11000 .
b1100 &
b1001 %
b1001 )
0#
#715
b100 "
b10011 '
b1101 &
b10 %
b1110 )
b110 +
1#
#720
b10000 '
0#
#725
b1 "
b10001 '
b1100 &
b1010 %
b1010 )
b0 +
1#
#730
b1 "
b10010 '
b11 &
b10 %
b10 )
0#
#735
b1101 '
1#
#740
b1 "
b1110 '
1,
b11001 .
b1100 &
b1001 %
b1001 )
0#
#745
b1000 "
b10011 '
b1101 &
b10 %
b1110 )
b110 +
1#
#750
b1111 '
0#
#755
b1 "
b10010 '
b100 &
b10 )
b0 +
1#
#760
b1101 '
0#
#765
b1 "
b1110 '
0,
b11010 .
b1100 &
b1001 %
b1001 )
1#
#770
b100 "
b10011 '
b1101 &
b10 %
b1110 )
b110 +
0#
#775
b10000 '
1#
#780
b1 "
b10001 '
b1100 &
b1010 %
b1010 )
b0 +
0#
#785
b1 "
b10010 '
b11 &
b10 %
b10 )
1#
#790
b1101 '
0#
#795
b1 "
b1110 '
1,
b11011 .
b1100 &
b1001 %
b1001 )
1#
#800
b1000 "
b10011 '
b1101 &
b10 %
b1110 )
b110 +
0#
#805
b1111 '
1#
#810
b1 "
b10010 '
b100 &
b10 )
b0 +
0#
#815
b1101 '
1#
#820
b1 "
b1110 '
0,
b11100 .
b1100 &
b1001 %
b1001 )
0#
#825
b100 "
b10011 '
b1101 &
b10 %
b1110 )
b110 +
1#
#830
b10000 '
0#
#835
b1 "
b10001 '
b1100 &
b1010 %
b1010 )
b0 +
1#
#840
b1 "
b10010 '
b11 &
b10 %
b10 )
0#
#845
b1101 '
1#
#850
b1 "
b1110 '
1,
b11101 .
b1100 &
b1001 %
b1001 )
0#
#855
b100 "
b10011 '
b1101 &
b10 %
b1110 )
b110 +
1#
#860
b10000 '
0#
#865
b1 "
b10001 '
b1100 &
b1010 %
b1010 )
b0 +
1#
#870
b1 "
b10010 '
b11 &
b10 %
b10 )
0#
#875
b1101 '
1#
#880
b1 "
b1110 '
0,
b11110 .
b1100 &
b1001 %
b1001 )
0#
#885
b1000 "
b10011 '
b1101 &
b10 %
b1110 )
b110 +
1#
#890
b1111 '
0#
#895
b1 "
b10010 '
b100 &
b10 )
b0 +
1#
#900
b1101 '
0#
#905
b1 "
b1110 '
1,
b11111 .
b1100 &
b1001 %
b1001 )
1#
#910
b100 "
b10011 '
b1101 &
b10 %
b1110 )
b110 +
0#
#915
b10000 '
1#
#920
b1 "
b10001 '
b1100 &
b1010 %
b1010 )
b0 +
0#
#925
b1 "
b10010 '
b11 &
b10 %
b10 )
1#
#930
b1101 '
0#
#935
b1 "
b1110 '
0,
b100000 .
b1100 &
b1001 %
b1001 )
1#
#940
b100 "
b10011 '
b1101 &
b10 %
b1110 )
b110 +
0#
#945
b10000 '
1#
#950
b1 "
b10001 '
b1100 &
b1010 %
b1010 )
b0 +
0#
#955
b1 "
b10010 '
b11 &
b10 %
b10 )
1#
#960
b1101 '
0#
#965
b1 "
b1110 '
1,
b100001 .
b1100 &
b1001 %
b1001 )
1#
#970
b1000 "
b10011 '
b1101 &
b10 %
b1110 )
b110 +
0#
#975
b1111 '
1#
#980
b1 "
b10010 '
b100 &
b10 )
b0 +
0#
#985
b1101 '
1#
#990
b1 "
b1110 '
0,
b100010 .
b1100 &
b1001 %
b1001 )
0#
#995
b100 "
b10011 '
b1101 &
b10 %
b1110 )
b110 +
1#
#1000
b10000 '
0#
#1005
b1 "
b10001 '
b1100 &
b1010 %
b1010 )
b0 +
1#
#1010
b1 "
b10010 '
b11 &
b10 %
b10 )
0#
#1015
b1101 '
1#
#1020
b1 "
b1110 '
1,
b100011 .
b1100 &
b1001 %
b1001 )
0#
#1025
b1000 "
b10011 '
b1101 &
b10 %
b1110 )
b110 +
1#
#1030
b1111 '
0#
#1035
b1 "
b10010 '
b100 &
b10 )
b0 +
1#
#1040
b1101 '
0#
#1045
b1 "
b1110 '
0,
b100100 .
b1100 &
b1001 %
b1001 )
1#
#1050
b100 "
b10011 '
b1101 &
b10 %
b1110 )
b110 +
0#
#1055
b10000 '
1#
#1060
b1 "
b10001 '
b1100 &
b1010 %
b1010 )
b0 +
0#
#1065
b1 "
b10010 '
b11 &
b10 %
b10 )
1#
#1070
b1101 '
0#
#1075
b1 "
b1110 '
1,
b100101 .
b1100 &
b1001 %
b1001 )
1#
#1080
b100 "
b10011 '
b1101 &
b10 %
b1110 )
b110 +
0#
#1085
b10000 '
1#
#1090
b1 "
b10001 '
b1100 &
b1010 %
b1010 )
b0 +
0#
#1095
b1 "
b10010 '
b11 &
b10 %
b10 )
1#
#1100
b1101 '
0#
#1105
b1 "
b1110 '
0,
b100110 .
b1100 &
b1001 %
b1001 )
1#
#1110
b1000 "
b10011 '
b1101 &
b10 %
b1110 )
b110 +
0#
#1115
b1111 '
1#
#1120
b1 "
b10010 '
b100 &
b10 )
b0 +
0#
#1125
b1101 '
1#
#1130
b1 "
b1110 '
1,
b100111 .
b1100 &
b1001 %
b1001 )
0#
#1135
b100 "
b10011 '
b1101 &
b10 %
b1110 )
b110 +
1#
#1140
b10000 '
0#
#1145
b1 "
b10001 '
b1100 &
b1010 %
b1010 )
b0 +
1#
#1150
b1 "
b10010 '
b11 &
b10 %
b10 )
0#
#1155
b1101 '
1#
#1160
b1 "
b1110 '
0,
b101000 .
b1100 &
b1001 %
b1001 )
0#
#1165
b1000 "
b10011 '
b1101 &
b10 %
b1110 )
b110 +
1#
#1170
b1111 '
0#
#1175
b1 "
b10010 '
b100 &
b10 )
b0 +
1#
#1180
b1101 '
0#
#1185
b1 "
b1110 '
1,
b101001 .
b1100 &
b1001 %
b1001 )
1#
#1190
b100 "
b10011 '
b1101 &
b10 %
b1110 )
b110 +
0#
#1195
b10000 '
1#
#1200
b1 "
b10001 '
b1100 &
b1010 %
b1010 )
b0 +
0#
#1205
b1 "
b10010 '
b11 &
b10 %
b10 )
1#
#1210
b1101 '
0#
#1215
b1 "
b1110 '
0,
b101010 .
b1100 &
b1001 %
b1001 )
1#
#1220
b100 "
b10011 '
b1101 &
b10 %
b1110 )
b110 +
0#
#1225
b10000 '
1#
#1230
b1 "
b10001 '
b1100 &
b1010 %
b1010 )
b0 +
0#
#1235
b1 "
b10010 '
b11 &
b10 %
b10 )
1#
#1240
b1101 '
0#
#1245
b1 "
b1110 '
1,
b101011 .
b1100 &
b1001 %
b1001 )
1#
#1250
b1000 "
b10011 '
b1101 &
b10 %
b1110 )
b110 +
0#
#1255
b1111 '
1#
#1260
b1 "
b10010 '
b100 &
b10 )
b0 +
0#
#1265
b1101 '
1#
#1270
b1 "
b1110 '
0,
b101100 .
b1100 &
b1001 %
b1001 )
0#
#1275
b100 "
b10011 '
b1101 &
b10 %
b1110 )
b110 +
1#
#1280
b10000 '
0#
#1285
b1 "
b10001 '
b1100 &
b1010 %
b1010 )
b0 +
1#
#1290
b1 "
b10010 '
b11 &
b10 %
b10 )
0#
#1295
b1101 '
1#
#1300
b1 "
b1110 '
1,
b101101 .
b1100 &
b1001 %
b1001 )
0#
#1305
b1000 "
b10011 '
b1101 &
b10 %
b1110 )
b110 +
1#
#1310
b1111 '
0#
#1315
b1 "
b10010 '
b100 &
b10 )
b0 +
1#
#1320
b1101 '
0#
#1325
b1 "
b1110 '
0,
b101110 .
b1100 &
b1001 %
b1001 )
1#
#1330
b100 "
b10011 '
b1101 &
b10 %
b1110 )
b110 +
0#
#1335
b10000 '
1#
#1340
b1 "
b10001 '
b1100 &
b1010 %
b1010 )
b0 +
0#
#1345
b1 "
b10010 '
b11 &
b10 %
b10 )
1#
#1350
b1101 '
0#
#1355
b1 "
b1110 '
1,
b101111 .
b1100 &
b1001 %
b1001 )
1#
#1360
b100 "
b10011 '
b1101 &
b10 %
b1110 )
b110 +
0#
#1365
b10000 '
1#
#1370
b1 "
b10001 '
b1100 &
b1010 %
b1010 )
b0 +
0#
#1375
b1 "
b10010 '
b11 &
b10 %
b10 )
1#
#1380
b1101 '
0#
#1385
b1 "
b1110 '
0,
b110000 .
b1100 &
b1001 %
b1001 )
1#
#1390
b1000 "
b10011 '
b1101 &
b10 %
b1110 )
b110 +
0#
#1395
b1111 '
1#
#1400
b1 "
b10010 '
b100 &
b10 )
b0 +
0#
#1405
b1101 '
1#
#1410
b1 "
b1110 '
1,
b110001 .
b1100 &
b1001 %
b1001 )
0#
#1415
b100 "
b10011 '
b1101 &
b10 %
b1110 )
b110 +
1#
#1420
b10000 '
0#
#1425
b1 "
b10001 '
b1100 &
b1010 %
b1010 )
b0 +
1#
#1430
b1 "
b10010 '
b11 &
b10 %
b10 )
0#
#1435
b1101 '
1#
#1440
b1 "
b1110 '
0,
b110010 .
b1100 &
b1001 %
b1001 )
0#
#1445
b1000 "
b10011 '
b1101 &
b10 %
b1110 )
b110 +
1#
#1450
b1111 '
0#
#1455
b1 "
b10010 '
b100 &
b10 )
b0 +
1#
#1460
b1101 '
0#
#1465
b1 "
b1110 '
1,
b110011 .
b1100 &
b1001 %
b1001 )
1#
#1470
b100 "
b10011 '
b1101 &
b10 %
b1110 )
b110 +
0#
#1475
b10000 '
1#
#1480
b1 "
b10001 '
b1100 &
b1010 %
b1010 )
b0 +
0#
#1485
b1 "
b10010 '
b11 &
b10 %
b10 )
1#
#1490
b0 -
b0 '
0#
